rest_framework_json_api/__init__.py
rest_framework_json_api/compat.py
rest_framework_json_api/exceptions.py
rest_framework_json_api/filters.py
rest_framework_json_api/metadata.py
rest_framework_json_api/pagination.py
rest_framework_json_api/parsers.py
rest_framework_json_api/relations.py
rest_framework_json_api/renderers.py
rest_framework_json_api/serializers.py
rest_framework_json_api/settings.py
rest_framework_json_api/utils.py
rest_framework_json_api/views.py
rest_framework_json_api/__pycache__/__init__.cpython-312.pyc
rest_framework_json_api/__pycache__/compat.cpython-312.pyc
rest_framework_json_api/__pycache__/exceptions.cpython-312.pyc
rest_framework_json_api/__pycache__/filters.cpython-312.pyc
rest_framework_json_api/__pycache__/metadata.cpython-312.pyc
rest_framework_json_api/__pycache__/pagination.cpython-312.pyc
rest_framework_json_api/__pycache__/parsers.cpython-312.pyc
rest_framework_json_api/__pycache__/relations.cpython-312.pyc
rest_framework_json_api/__pycache__/renderers.cpython-312.pyc
rest_framework_json_api/__pycache__/serializers.cpython-312.pyc
rest_framework_json_api/__pycache__/settings.cpython-312.pyc
rest_framework_json_api/__pycache__/utils.cpython-312.pyc
rest_framework_json_api/__pycache__/views.cpython-312.pyc
rest_framework_json_api/django_filters/__init__.py
rest_framework_json_api/django_filters/backends.py
rest_framework_json_api/django_filters/__pycache__/__init__.cpython-312.pyc
rest_framework_json_api/django_filters/__pycache__/backends.cpython-312.pyc
rest_framework_json_api/schemas/__init__.py
rest_framework_json_api/schemas/openapi.py
rest_framework_json_api/schemas/__pycache__/__init__.cpython-312.pyc
rest_framework_json_api/schemas/__pycache__/openapi.cpython-312.pyc
rest_framework_json_api/templates/rest_framework_json_api/api.html
rest_framework_json_api/templates/rest_framework_json_api/includes.html
djangorestframework_jsonapi-8.1.0.dist-info/AUTHORS
djangorestframework_jsonapi-8.1.0.dist-info/LICENSE
djangorestframework_jsonapi-8.1.0.dist-info/METADATA
djangorestframework_jsonapi-8.1.0.dist-info/WHEEL
djangorestframework_jsonapi-8.1.0.dist-info/top_level.txt
djangorestframework_jsonapi-8.1.0.dist-info/RECORD
