Metadata-Version: 2.1
Name: djangorestframework-jsonapi
Version: 8.1.0
Summary: A Django REST framework API adapter for the JSON:API spec.
Home-page: https://github.com/django-json-api/django-rest-framework-json-api
Author: Jerel Unruh
Author-email: 
License: BSD
Project-URL: Documentation, https://django-rest-framework-json-api.readthedocs.org/
Project-URL: Changelog, https://github.com/django-json-api/django-rest-framework-json-api/blob/main/CHANGELOG.md
Project-URL: Source, https://github.com/django-json-api/django-rest-framework-json-api
Project-URL: Tracker, https://github.com/django-json-api/django-rest-framework-json-api/issues
Classifier: Development Status :: 5 - Production/Stable
Classifier: Environment :: Web Environment
Classifier: Framework :: Django
Classifier: Intended Audience :: Developers
Classifier: License :: OSI Approved :: BSD License
Classifier: Operating System :: OS Independent
Classifier: Programming Language :: Python
Classifier: Programming Language :: Python :: 3
Classifier: Programming Language :: Python :: 3.9
Classifier: Programming Language :: Python :: 3.10
Classifier: Programming Language :: Python :: 3.11
Classifier: Programming Language :: Python :: 3.12
Classifier: Programming Language :: Python :: 3.13
Classifier: Programming Language :: Python :: 3.14
Classifier: Topic :: Internet :: WWW/HTTP
Classifier: Topic :: Software Development :: Libraries :: Application Frameworks
Classifier: Topic :: Software Development :: Libraries :: Python Modules
Requires-Python: >=3.9
License-File: LICENSE
License-File: AUTHORS
Requires-Dist: inflection >=0.5.0
Requires-Dist: djangorestframework >=3.15
Requires-Dist: django >=4.2
Provides-Extra: django-filter
Requires-Dist: django-filter >=2.4 ; extra == 'django-filter'
Provides-Extra: django-polymorphic
Requires-Dist: django-polymorphic >=4.0.0 ; extra == 'django-polymorphic'
